turing_calc/__init__.py
turing_calc/calculator.py
turing_calc/main.py
turing_calc-0.1.3.dist-info/entry_points.txt
turing_calc-0.1.3.dist-info/METADATA
turing_calc-0.1.3.dist-info/WHEEL
turing_calc-0.1.3.dist-info/RECORD
