Metadata-Version: 2.1
Name: turing-calc
Version: 0.1.3
Summary: 
License: MIT
Author: qintas
Author-email: giandrius@gmail.com
Requires-Python: >=3.12,<4.0
Classifier: License :: OSI Approved :: MIT License
Classifier: Programming Language :: Python :: 3
Classifier: Programming Language :: Python :: 3.12
Project-URL: homepage, https://github.com/TuringCollegeSubmissions/andrig-DS.v3.1.2.5
Project-URL: repository, https://github.com/TuringCollegeSubmissions/andrig-DS.v3.1.2.5
